{
  "name": "The Arc",
  "key": "arc",
  "description": "Curved approach with shortcuts over the top. Flank or get flanked.",
  "palette": [
    1054776,
    1581120,
    2629696,
    4724784,
    3678272,
    2629696,
    1581120,
    1054776
  ],
  "rooms": [
    {
      "id": "spawn_a",
      "team": "A",
      "x": -1200,
      "y": 0,
      "z": 450,
      "r": 330
    },
    {
      "id": "arc_1",
      "team": null,
      "x": -900,
      "y": 150,
      "z": -450,
      "r": 270
    },
    {
      "id": "arc_2",
      "team": null,
      "x": -450,
      "y": 300,
      "z": -900,
      "r": 270
    },
    {
      "id": "arc_3",
      "team": null,
      "x": 0,
      "y": 450,
      "z": -1050,
      "r": 300
    },
    {
      "id": "arc_4",
      "team": null,
      "x": 450,
      "y": 300,
      "z": -900,
      "r": 270
    },
    {
      "id": "arc_5",
      "team": null,
      "x": 900,
      "y": 150,
      "z": -450,
      "r": 270
    },
    {
      "id": "spawn_b",
      "team": "B",
      "x": 1200,
      "y": 0,
      "z": 450,
      "r": 330
    }
  ],
  "tunnels": [
    {
      "path": [
        {
          "x": -1200,
          "y": 0,
          "z": 450
        },
        {
          "x": -900,
          "y": 150,
          "z": -450
        }
      ],
      "r": 180
    },
    {
      "path": [
        {
          "x": -900,
          "y": 150,
          "z": -450
        },
        {
          "x": -450,
          "y": 300,
          "z": -900
        }
      ],
      "r": 180
    },
    {
      "path": [
        {
          "x": -450,
          "y": 300,
          "z": -900
        },
        {
          "x": 0,
          "y": 450,
          "z": -1050
        }
      ],
      "r": 180
    },
    {
      "path": [
        {
          "x": 0,
          "y": 450,
          "z": -1050
        },
        {
          "x": 450,
          "y": 300,
          "z": -900
        }
      ],
      "r": 180
    },
    {
      "path": [
        {
          "x": 450,
          "y": 300,
          "z": -900
        },
        {
          "x": 900,
          "y": 150,
          "z": -450
        }
      ],
      "r": 180
    },
    {
      "path": [
        {
          "x": 900,
          "y": 150,
          "z": -450
        },
        {
          "x": 1200,
          "y": 0,
          "z": 450
        }
      ],
      "r": 180
    },
    {
      "path": [
        {
          "x": -900,
          "y": 150,
          "z": -450
        },
        {
          "x": 0,
          "y": 450,
          "z": -1050
        }
      ],
      "r": 180
    },
    {
      "path": [
        {
          "x": 0,
          "y": 450,
          "z": -1050
        },
        {
          "x": 900,
          "y": 150,
          "z": -450
        }
      ],
      "r": 180
    },
    {
      "path": [
        {
          "x": -450,
          "y": 300,
          "z": -900
        },
        {
          "x": 450,
          "y": 300,
          "z": -900
        }
      ],
      "r": 180
    }
  ]
}
